NeuroConn/__init__.py
NeuroConn/data/__init__.py
NeuroConn/data/example_datasets.py
NeuroConn/gradient/__init__.py
NeuroConn/gradient/dispersion.py
NeuroConn/gradient/gradient.py
NeuroConn/gradient/hcp_grads_schaefer1000_pearson_95th.npy
NeuroConn/gradient/margulies_grads_schaefer1000.npy
NeuroConn/preprocessing/__init__.py
NeuroConn/preprocessing/preprocessing.py
tests/__init__.py
tests/test_neuroconn.py
NeuroConn-0.1.0a8.dist-info/METADATA
NeuroConn-0.1.0a8.dist-info/WHEEL
NeuroConn-0.1.0a8.dist-info/top_level.txt
NeuroConn-0.1.0a8.dist-info/RECORD
