Metadata-Version: 2.1
Name: NeuroConn
Version: 0.1.0a8
Summary: A BIDS toolbox for connectivity & gradient analyses.
Home-page: https://github.com/victoris93/NeuroConn
Author: Victoria Shevchenko
Author-email: shevchenko682@gmail.com
License: UNKNOWN
Keywords: fmriprep,BIDS,connectivity,gradients,dispersion
Platform: UNKNOWN
Classifier: Development Status :: 3 - Alpha
Classifier: Intended Audience :: Science/Research
Classifier: License :: OSI Approved :: MIT License
Classifier: Programming Language :: Python :: 3
Classifier: Programming Language :: Python :: 3.6
Classifier: Programming Language :: Python :: 3.7
Classifier: Programming Language :: Python :: 3.8
Classifier: Programming Language :: Python :: 3.9
Requires-Python: >=3.6
Requires-Dist: nilearn
Requires-Dist: numpy
Requires-Dist: pandas
Requires-Dist: scikit-learn
Requires-Dist: nibabel
Requires-Dist: brainspace
Requires-Dist: gdown
Requires-Dist: fmriprep-docker
Requires-Dist: hcp-utils
